vitortools/__init__.py
vitortools/vitortools.py
vitortools-0.0.3.dist-info/METADATA
vitortools-0.0.3.dist-info/WHEEL
vitortools-0.0.3.dist-info/top_level.txt
vitortools-0.0.3.dist-info/RECORD
